freecad_mcp/__init__.py
freecad_mcp/_version.py
freecad_mcp/config.py
freecad_mcp/py.typed
freecad_mcp/server.py
freecad_mcp/bridge/__init__.py
freecad_mcp/bridge/base.py
freecad_mcp/bridge/embedded.py
freecad_mcp/bridge/socket.py
freecad_mcp/bridge/xmlrpc.py
freecad_mcp/freecad_plugin/__init__.py
freecad_mcp/freecad_plugin/gui_startup.py
freecad_mcp/freecad_plugin/headless_server.py
freecad_mcp/freecad_plugin/server.py
freecad_mcp/prompts/__init__.py
freecad_mcp/prompts/freecad.py
freecad_mcp/resources/__init__.py
freecad_mcp/resources/freecad.py
freecad_mcp/tools/__init__.py
freecad_mcp/tools/documents.py
freecad_mcp/tools/execution.py
freecad_mcp/tools/export.py
freecad_mcp/tools/macros.py
freecad_mcp/tools/objects.py
freecad_mcp/tools/partdesign.py
freecad_mcp/tools/view.py
freecad_mcp/utils/__init__.py
freecad_robust_mcp-0.5.0b0.dist-info/METADATA
freecad_robust_mcp-0.5.0b0.dist-info/WHEEL
freecad_robust_mcp-0.5.0b0.dist-info/entry_points.txt
freecad_robust_mcp-0.5.0b0.dist-info/licenses/LICENSE
freecad_robust_mcp-0.5.0b0.dist-info/RECORD
