Metadata-Version: 2.4
Name: freecad-robust-mcp
Version: 0.5.0b0
Summary: MCP (Model Context Protocol) server for FreeCAD integration with Claude Code and other AI assistants
Project-URL: Homepage, https://github.com/spkane/freecad-robust-mcp-and-more
Project-URL: Documentation, https://github.com/spkane/freecad-robust-mcp-and-more#readme
Project-URL: Repository, https://github.com/spkane/freecad-robust-mcp-and-more.git
Project-URL: Issues, https://github.com/spkane/freecad-robust-mcp-and-more/issues
Project-URL: Changelog, https://github.com/spkane/freecad-robust-mcp-and-more/blob/main/CHANGELOG.md
Project-URL: Docker Hub, https://hub.docker.com/r/spkane/freecad-robust-mcp
Author-email: "Sean P. Kane" <spkane@gmail.com>
Maintainer-email: "Sean P. Kane" <spkane@gmail.com>
License-Expression: MIT
License-File: LICENSE
Keywords: 3d-modeling,3d-printing,ai,automation,cad,claude,claude-code,freecad,llm,mcp,model-context-protocol,parametric-design
Classifier: Development Status :: 4 - Beta
Classifier: Environment :: Console
Classifier: Framework :: AsyncIO
Classifier: Intended Audience :: Developers
Classifier: Intended Audience :: Manufacturing
Classifier: Intended Audience :: Science/Research
Classifier: License :: OSI Approved :: MIT License
Classifier: Natural Language :: English
Classifier: Operating System :: MacOS
Classifier: Operating System :: Microsoft :: Windows
Classifier: Operating System :: OS Independent
Classifier: Operating System :: POSIX :: Linux
Classifier: Programming Language :: Python :: 3
Classifier: Programming Language :: Python :: 3 :: Only
Classifier: Programming Language :: Python :: 3.11
Classifier: Programming Language :: Python :: 3.12
Classifier: Programming Language :: Python :: 3.13
Classifier: Topic :: Scientific/Engineering
Classifier: Topic :: Scientific/Engineering :: Visualization
Classifier: Topic :: Software Development :: Libraries :: Python Modules
Classifier: Typing :: Typed
Requires-Python: >=3.11
Requires-Dist: mcp>=1.25.0
Requires-Dist: pydantic-settings>=2.7.0
Requires-Dist: pydantic>=2.10.0
Provides-Extra: dev
Requires-Dist: bandit[toml]>=1.8.0; extra == 'dev'
Requires-Dist: build>=1.2.0; extra == 'dev'
Requires-Dist: md-toc>=9.0.0; extra == 'dev'
Requires-Dist: mkdocs-material>=9.5.0; extra == 'dev'
Requires-Dist: mkdocs>=1.6.0; extra == 'dev'
Requires-Dist: mkdocstrings[python]>=0.27.0; extra == 'dev'
Requires-Dist: mypy>=1.14.0; extra == 'dev'
Requires-Dist: pre-commit>=4.0.0; extra == 'dev'
Requires-Dist: pytest-asyncio>=0.25.0; extra == 'dev'
Requires-Dist: pytest-cov>=6.0.0; extra == 'dev'
Requires-Dist: pytest-timeout>=2.3.0; extra == 'dev'
Requires-Dist: pytest>=8.3.0; extra == 'dev'
Requires-Dist: ruff>=0.8.0; extra == 'dev'
Requires-Dist: safety>=3.2.0; extra == 'dev'
Requires-Dist: twine>=6.0.0; extra == 'dev'
